[
  { "id": 1,  "name": "Collectible Item #1",  "image": "imgs/image1.jpeg",  "price": "15.00", "category": "collectible" },
  { "id": 2,  "name": "Collectible Item #2",  "image": "imgs/image2.jpeg",  "price": "15.00", "category": "collectible" },
  { "id": 3,  "name": "Collectible Item #3",  "image": "imgs/image3.jpeg",  "price": "15.00", "category": "collectible" },
  { "id": 4,  "name": "Collectible Item #4",  "image": "imgs/image4.jpeg",  "price": "15.00", "category": "collectible" },
  { "id": 5,  "name": "Collectible Item #5",  "image": "imgs/image5.jpeg",  "price": "15.00", "category": "collectible" },
  { "id": 6,  "name": "Collectible Item #6",  "image": "imgs/image6.jpeg",  "price": "15.00", "category": "collectible" },
  { "id": 7,  "name": "Collectible Item #7",  "image": "imgs/image7.jpeg",  "price": "13.00", "category": "limited" },
  { "id": 8,  "name": "Collectible Item #8",  "image": "imgs/image8.jpeg",  "price": "13.00", "category": "limited" },
  { "id": 9,  "name": "Collectible Item #9",  "image": "imgs/image9.jpeg",  "price": "15.00", "category": "collectible" },
  { "id": 10, "name": "Collectible Item #10", "image": "imgs/image10.jpeg", "price": "15.00", "category": "collectible" },
  { "id": 11, "name": "Collectible Item #11", "image": "imgs/image11.jpeg", "price": "15.00", "category": "collectible" },
  { "id": 12, "name": "Collectible Item #12", "image": "imgs/image12.jpeg", "price": "18.00", "category": "limited" },
  { "id": 13, "name": "Collectible Item #13", "image": "imgs/image13.jpeg", "price": "15.00", "category": "collectible" },
  { "id": 14, "name": "Collectible Item #14", "image": "imgs/image14.jpeg", "price": "15.00", "category": "collectible" },
  { "id": 15, "name": "Collectible Item #15", "image": "imgs/image15.jpeg", "price": "12.99", "category": "collectible" },
  { "id": 16, "name": "Collectible Item #16", "image": "imgs/image16.jpeg", "price": "15.00", "category": "collectible" },
  { "id": 17, "name": "Collectible Item #17", "image": "imgs/image17.jpeg", "price": "15.00", "category": "collectible" },
  { "id": 18, "name": "Collectible Item #18", "image": "imgs/image18.jpeg", "price": "18.00", "category": "limited" },
  { "id": 19, "name": "Collectible Item #19", "image": "imgs/image19.jpeg", "price": "15.00", "category": "collectible" },
  { "id": 20, "name": "Collectible Item #20", "image": "imgs/image20.jpeg", "price": "15.00", "category": "collectible" },
  { "id": 21, "name": "Collectible Item #21", "image": "imgs/image21.jpeg", "price": "15.00", "category": "collectible" },
  { "id": 22, "name": "Collectible Item #22", "image": "imgs/image22.jpeg", "price": "13.00", "category": "limited" },
  { "id": 23, "name": "Collectible Item #23", "image": "imgs/image23.jpeg", "price": "15.00", "category": "collectible" },
  { "id": 24, "name": "Collectible Item #24", "image": "imgs/image24.jpeg", "price": "15.00", "category": "collectible" },
  { "id": 25, "name": "Collectible Item #25", "image": "imgs/image25.jpeg", "price": "15.00", "category": "collectible" },
  { "id": 26, "name": "Collectible Item #26", "image": "imgs/image26.jpeg", "price": "18.00", "category": "limited" },
  { "id": 27, "name": "Collectible Item #27", "image": "imgs/image27.jpeg", "price": "15.00", "category": "collectible" },
  { "id": 28, "name": "Collectible Item #28", "image": "imgs/image28.jpeg", "price": "15.00", "category": "collectible" },
  { "id": 29, "name": "Collectible Item #29", "image": "imgs/image29.jpeg", "price": "15.00", "category": "collectible" },
  { "id": 30, "name": "Collectible Item #30", "image": "imgs/image30.jpeg", "price": "15.00", "category": "collectible" }
]